alu_struct_model.v
`timescale 1ns/1ps

module full_adder(
    input A,
    input B,
    input Cin,
    output Sum,
    output Cout
);

wire w1, w2, w3;

xor (w1, A, B);
xor (Sum, w1, Cin);
and (w2, A, B);
and (w3, w1, Cin);
or (Cout, w2, w3);

endmodule


module adder_4bit(
    input [3:0] A,
    input [3:0] B,
    output [3:0] Sum,
    output Carry
);

wire c1, c2, c3;

full_adder fa0(A[0], B[0], 1'b0, Sum[0], c1);
full_adder fa1(A[1], B[1], c1, Sum[1], c2);
full_adder fa2(A[2], B[2], c2, Sum[2], c3);
full_adder fa3(A[3], B[3], c3, Sum[3], Carry);

endmodule


module multiplier_4bit(
    input [3:0] A,
    input [3:0] B,
    output [7:0] Product
);

wire [7:0] pp0;
wire [7:0] pp1;
wire [7:0] pp2;
wire [7:0] pp3;

wire [7:0] s1;
wire [7:0] s2;

assign pp0 = B[0] ? {4'b0000, A}       : 8'b00000000;
assign pp1 = B[1] ? {3'b000, A, 1'b0}  : 8'b00000000;
assign pp2 = B[2] ? {2'b00, A, 2'b00}  : 8'b00000000;
assign pp3 = B[3] ? {1'b0, A, 3'b000}  : 8'b00000000;

assign s1 = pp0 + pp1;
assign s2 = s1 + pp2;
assign Product = s2 + pp3;

endmodule


module divider_4bit(
    input [3:0] A,
    input [3:0] B,
    output reg [3:0] Quotient
);

reg [4:0] remainder;
reg [3:0] quotient;
integer i;

always @(*) begin
    remainder = 5'b00000;
    quotient = 4'b0000;

    if (B != 4'b0000) begin
        for (i = 3; i >= 0; i = i - 1) begin
            remainder = {remainder[3:0], A[i]};

            if (remainder >= {1'b0, B}) begin
                remainder = remainder - {1'b0, B};
                quotient[i] = 1'b1;
            end
        end
    end

    Quotient = quotient;
end

endmodule



module alu_struct_model(
    input [3:0] A,
    input [3:0] B,
    input [2:0] Sel,
    output [3:0] Result,
    output Carry,
    output Zero
);

wire [3:0] add_result;
wire [3:0] sub_result;
wire [3:0] and_result;
wire [3:0] or_result;

wire [7:0] mul_result;
wire [3:0] div_result;

wire add_carry;
wire sub_borrow;

adder_4bit ADD(
    .A(A),
    .B(B),
    .Sum(add_result),
    .Carry(add_carry)
);

assign sub_result = A - B;
assign sub_borrow = (A < B);

assign and_result = A & B;
assign or_result = A | B;

multiplier_4bit MUL(
    .A(A),
    .B(B),
    .Product(mul_result)
);

divider_4bit DIV(
    .A(A),
    .B(B),
    .Quotient(div_result)
);

assign Result =
    (Sel == 3'b000) ? add_result      :
    (Sel == 3'b001) ? sub_result      :
    (Sel == 3'b010) ? and_result      :
    (Sel == 3'b011) ? or_result       :
    (Sel == 3'b100) ? div_result      :
    (Sel == 3'b101) ? mul_result[3:0] :
    (Sel == 3'b110) ? (A << 1)        :
    (Sel == 3'b111) ? (A >> 1)        :
                       4'b0000;

assign Carry =
    (Sel == 3'b000) ? add_carry :
    (Sel == 3'b001) ? sub_borrow :
                       1'b0;

assign Zero = (Result == 4'b0000);

endmodule

alu_struct_model_tb.v
`timescale 1ns/1ps

module alu_struct_model_tb;

reg [3:0] A;
reg [3:0] B;
reg [2:0] Sel;

wire [3:0] Result;
wire Carry;
wire Zero;

alu_struct_model uut(
    .A(A),
    .B(B),
    .Sel(Sel),
    .Result(Result),
    .Carry(Carry),
    .Zero(Zero)
);

initial begin

    $dumpfile("alu_struct.vcd");
    $dumpvars(0, alu_struct_model_tb);

    $monitor("Time=%0t A=%d B=%d Sel=%b Result=%d Carry=%b Zero=%b",
             $time, A, B, Sel, Result, Carry, Zero);

    A = 4'd5;
    B = 4'd3;
    Sel = 3'b000;
    #10;

    A = 4'd8;
    B = 4'd2;
    Sel = 3'b001;
    #10;

    A = 4'b1100;
    B = 4'b1010;
    Sel = 3'b010;
    #10;

    A = 4'b1100;
    B = 4'b1010;
    Sel = 3'b011;
    #10;

    A = 4'd15;
    B = 4'd2;
    Sel = 3'b100;
    #10;

    A = 4'd3;
    B = 4'd4;
    Sel = 3'b101;
    #10;

    A = 4'b0011;
    B = 4'b0000;
    Sel = 3'b110;
    #10;

    A = 4'b1000;
    B = 4'b0000;
    Sel = 3'b111;
    #10;

    A = 4'd0;
    B = 4'd0;
    Sel = 3'b000;
    #10;

    A = 4'd10;
    B = 4'd0;
    Sel = 3'b100;
    #10;

    A = 4'd15;
    B = 4'd15;
    Sel = 3'b101;
    #10;

    A = 4'd15;
    B = 4'd4;
    Sel = 3'b100;
    #10;

    $finish;

end

endmodule

alu_struct.vcd
$date
	Fri Oct 02 11:47:03 2026
$end
$version
	Icarus Verilog
$end
$timescale
	1ps
$end
$scope module alu_struct_model_tb $end
$var wire 1 ! Zero $end
$var wire 4 " Result [3:0] $end
$var wire 1 # Carry $end
$var reg 4 $ A [3:0] $end
$var reg 4 % B [3:0] $end
$var reg 3 & Sel [2:0] $end
$scope module uut $end
$var wire 4 ' A [3:0] $end
$var wire 4 ( B [3:0] $end
$var wire 3 ) Sel [2:0] $end
$var wire 4 * and_result [3:0] $end
$var wire 4 + or_result [3:0] $end
$var wire 4 , sub_result [3:0] $end
$var wire 1 - sub_borrow $end
$var wire 8 . mul_result [7:0] $end
$var wire 4 / div_result [3:0] $end
$var wire 4 0 add_result [3:0] $end
$var wire 1 1 add_carry $end
$var wire 1 ! Zero $end
$var wire 4 2 Result [3:0] $end
$var wire 1 # Carry $end
$scope module ADD $end
$var wire 4 3 A [3:0] $end
$var wire 4 4 B [3:0] $end
$var wire 1 5 c3 $end
$var wire 1 6 c2 $end
$var wire 1 7 c1 $end
$var wire 4 8 Sum [3:0] $end
$var wire 1 1 Carry $end
$scope module fa0 $end
$var wire 1 9 A $end
$var wire 1 : B $end
$var wire 1 ; Cin $end
$var wire 1 7 Cout $end
$var wire 1 < Sum $end
$var wire 1 = w1 $end
$var wire 1 > w2 $end
$var wire 1 ? w3 $end
$upscope $end
$scope module fa1 $end
$var wire 1 @ A $end
$var wire 1 A B $end
$var wire 1 7 Cin $end
$var wire 1 6 Cout $end
$var wire 1 B Sum $end
$var wire 1 C w1 $end
$var wire 1 D w2 $end
$var wire 1 E w3 $end
$upscope $end
$scope module fa2 $end
$var wire 1 F A $end
$var wire 1 G B $end
$var wire 1 6 Cin $end
$var wire 1 5 Cout $end
$var wire 1 H Sum $end
$var wire 1 I w1 $end
$var wire 1 J w2 $end
$var wire 1 K w3 $end
$upscope $end
$scope module fa3 $end
$var wire 1 L A $end
$var wire 1 M B $end
$var wire 1 5 Cin $end
$var wire 1 1 Cout $end
$var wire 1 N Sum $end
$var wire 1 O w1 $end
$var wire 1 P w2 $end
$var wire 1 Q w3 $end
$upscope $end
$upscope $end
$scope module DIV $end
$var wire 4 R A [3:0] $end
$var wire 4 S B [3:0] $end
$var reg 4 T Quotient [3:0] $end
$var reg 4 U quotient [3:0] $end
$var reg 5 V remainder [4:0] $end
$var integer 32 W i [31:0] $end
$upscope $end
$scope module MUL $end
$var wire 4 X A [3:0] $end
$var wire 4 Y B [3:0] $end
$var wire 8 Z s2 [7:0] $end
$var wire 8 [ s1 [7:0] $end
$var wire 8 \ pp3 [7:0] $end
$var wire 8 ] pp2 [7:0] $end
$var wire 8 ^ pp1 [7:0] $end
$var wire 8 _ pp0 [7:0] $end
$var wire 8 ` Product [7:0] $end
$upscope $end
$upscope $end
$upscope $end
$enddefinitions $end
$comment Show the parameter values. $end
$dumpall
$end
#0
$dumpvars
b1111 `
b101 _
b1010 ^
b0 ]
b0 \
b1111 [
b1111 Z
b11 Y
b101 X
b11111111111111111111111111111111 W
b10 V
b1 U
b1 T
b11 S
b101 R
0Q
0P
0O
1N
0M
0L
1K
0J
1I
0H
0G
1F
1E
0D
1C
0B
1A
0@
0?
1>
0=
0<
0;
1:
19
b1000 8
17
16
15
b11 4
b101 3
b1000 2
01
b1000 0
b1 /
b1111 .
0-
b10 ,
b111 +
b1 *
b0 )
b11 (
b101 '
b0 &
b11 %
b101 $
0#
b1000 "
0!
$end
#10000
06
1B
0E
05
01
07
0H
0K
b1010 0
b1010 8
1N
0Q
0>
0I
1O
b110 "
b110 2
0:
b0 *
b1010 +
09
0F
1L
b100 /
b100 T
b11111111111111111111111111111111 W
b100 U
b0 V
b0 _
b10000 .
b10000 `
b10000 Z
b10000 [
b10000 ^
b1 &
b1 )
b10 %
b10 (
b10 4
b10 S
b10 Y
b110 ,
b1000 $
b1000 '
b1000 3
b1000 R
b1000 X
#20000
0N
11
b110 0
b110 8
1H
0O
1P
b1100000 \
0!
b1000 "
b1000 2
1I
1M
b1000 *
b1110 +
1F
b1 /
b1 T
b10 V
b11111111111111111111111111111111 W
b1 U
b1111000 .
b1111000 `
b11000 Z
b11000 [
b11000 ^
b10 &
b10 )
b1010 %
b1010 (
b1010 4
b1010 S
b1010 Y
b10 ,
b1100 $
b1100 '
b1100 3
b1100 R
b1100 X
#30000
b1110 "
b1110 2
b11 &
b11 )
#40000
1Q
15
b111 "
b111 2
0H
1K
0N
11
1<
b1 0
b1 8
0B
16
1O
0P
1=
0C
1D
0M
b10 *
b1111 +
19
1@
b111 /
b111 T
b11111111111111111111111111111111 W
b111 U
b1 V
b11110 Z
b11110 [
b11110 ^
b11110 .
b11110 `
b0 \
b100 &
b100 )
b10 %
b10 (
b10 4
b10 S
b10 Y
b1101 ,
b1111 $
b1111 '
b1111 3
b1111 R
b1111 X
#50000
b1100 "
b1100 2
05
1H
0K
01
1B
06
b111 0
b111 8
0N
0Q
1C
0D
b1100 ]
0O
0A
1G
b0 *
b111 +
0F
0L
b0 /
b0 T
b11111111111111111111111111111111 W
b0 U
b11 V
b1100 .
b1100 `
b1100 Z
b0 [
b0 ^
b101 &
b101 )
1-
b100 %
b100 (
b100 4
b100 S
b100 Y
b1111 ,
b11 $
b11 '
b11 3
b11 R
b11 X
#60000
b110 "
b110 2
b11 0
b11 8
0H
0I
b0 .
b0 `
b0 Z
b0 ]
b11 +
0G
b0 V
b110 &
b110 )
b11 ,
0-
b0 %
b0 (
b0 4
b0 S
b0 Y
#70000
b100 "
b100 2
0<
0B
b1000 0
b1000 8
1N
0=
0C
1O
b1000 +
09
0@
1L
b111 &
b111 )
b1000 ,
b1000 $
b1000 '
b1000 3
b1000 R
b1000 X
#80000
1!
b0 0
b0 8
0N
0O
b0 "
b0 2
b0 +
0L
b0 &
b0 )
b0 ,
b0 $
b0 '
b0 3
b0 R
b0 X
#90000
1B
b1010 0
b1010 8
1N
1C
1O
b1010 +
1@
1L
b100 &
b100 )
b1010 ,
b1010 $
b1010 '
b1010 3
b1010 R
b1010 X
#100000
0!
b1 "
b1 2
b1110 0
b1110 8
1H
16
11
17
15
0C
1D
0O
1P
b1111 _
b101101 [
b11110 ^
b1101001 Z
b111100 ]
b11100001 .
b11100001 `
b1111000 \
1>
1J
1:
1A
1G
1M
b1111 *
b1111 +
19
1F
b1 /
b1 T
b1 U
b0 V
b11111111111111111111111111111111 W
b101 &
b101 )
b1111 %
b1111 (
b1111 4
b1111 S
b1111 Y
b0 ,
b1111 $
b1111 '
b1111 3
b1111 R
b1111 X
#110000
b11 "
b11 2
0H
1<
07
1B
0E
06
b11 0
b11 8
0N
1Q
11
1=
0>
1C
0D
1O
0P
b0 _
b111100 Z
b0 [
b0 ^
b111100 .
b111100 `
b0 \
b100 *
0:
0A
0M
b11 /
b11 T
b11 V
b11111111111111111111111111111111 W
b11 U
b100 &
b100 )
b1011 ,
b100 %
b100 (
b100 4
b100 S
b100 Y
